simple_api_client/__init__.py
simple_api_client/simple_api_client.py
simple_api_client-1.0.8.dist-info/LICENSE
simple_api_client-1.0.8.dist-info/METADATA
simple_api_client-1.0.8.dist-info/WHEEL
simple_api_client-1.0.8.dist-info/top_level.txt
simple_api_client-1.0.8.dist-info/RECORD
