Metadata-Version: 2.1
Name: simple-api-client
Version: 1.0.8
Summary: A simple API client for connecting to remote services.
Home-page: https://github.com/ScholarPack/api-client
Author: ScholarPack
Author-email: dev@scholarpack.com
License: UNKNOWN
Platform: UNKNOWN
Classifier: Development Status :: 5 - Production/Stable 
Classifier: Programming Language :: Python :: 3
Classifier: License :: OSI Approved :: MIT License
Classifier: Operating System :: OS Independent
Requires-Python: >=3.6
License-File: LICENSE
Requires-Dist: cookie-manager
Requires-Dist: requests
Requires-Dist: werkzeug
